[
  {
    "id": 131,
    "test_number": 1,
    "question_number": 56,
    "question_text": "Kenji and Mary are members of a school committee that will be meeting this afternoon. The 6 members of the committee will be seated randomly around a circular table, What is the probability that Kenji and Mary will NOT sit next to each other at the meeting?",
    "choices": [
      "F. 1/5",
      "G. 1/3",
      "H. 2/3",
      "J. 3/5",
      "K. 4/5"
    ],
    "correct_answer": "J",
    "explanation": "Working through the problem step-by-step with the values 6, the correct answer is 3/5.",
    "question_type": "Organized Counting",
    "difficulty": null,
    "image_url": null,
    "chapter": "23",
    "lesson_id": "aaea35f0-81c0-4b3e-930c-d13edeeb3db5",
    "section": "math"
  },
  {
    "id": 132,
    "test_number": 1,
    "question_number": 57,
    "question_text": "The digit in the ones place of 2\u2078\u2078 is 6. What is the digit in the ones place of 2\u2079\u2070?",
    "choices": [
      "A. 0",
      "B. 2",
      "C. 4",
      "D. 6",
      "E. 8"
    ],
    "correct_answer": "C",
    "explanation": "Working through the problem step-by-step with the values 2, 6., 2, the correct answer is 4.",
    "question_type": "Repeating Patterns",
    "difficulty": null,
    "image_url": null,
    "chapter": "20",
    "lesson_id": "d946c7ef-0543-46fd-a938-79592c05c044",
    "section": "math"
  },
  {
    "id": 133,
    "test_number": 1,
    "question_number": 58,
    "question_text": "Which of the following expressions represents the area, in square coordinate units, of <i>\u25b3RST</i> shown in the standard <i>(x,y)</i> coordinate plane below?",
    "choices": [
      "F. 1/2<i>(c-a)(e-d)</i>",
      "G. 1/2<i>c(c-a)</i>",
      "H. 1/2<i>e(c-a)</i>",
      "J. 1/2<i>{(e-d)\u00b2+ (b-a)\u00b2}{(e-d)\u00b2+(b-c)\u00b2}</i>",
      "K. 1/2<i>{\u221a((e-d)\u00b2+ (b-a)\u00b2)}{\u221a((e-d)\u00b2+(b-c)\u00b2)}</i>"
    ],
    "correct_answer": "F",
    "explanation": "Following the mathematical operations, the answer is 1/2<i>(c-a)(e-d)</i>.",
    "question_type": "Geometry Part 2 - Area",
    "difficulty": null,
    "image_url": "https://rabavobdklnwvwsldbix.supabase.co/storage/v1/object/public/test-images/m58.jpg",
    "chapter": "4",
    "lesson_id": "d2ae4a84-cb54-4006-8dee-8c325e443c2d",
    "section": "math"
  },
  {
    "id": 134,
    "test_number": 1,
    "question_number": 59,
    "question_text": "In the complex numbers where <i>i</i>\u00b2=-1 what complex number <i> x</i> is a solution to the equation <i> x</i>(2+3<i>i</i>)=1",
    "choices": [
      "A. 2/13 - 3/13<i>i</i>",
      "B. 2/5 + 3/5<i>i</i>",
      "C. 1",
      "D. -1",
      "E. -<i>i</i>/13"
    ],
    "correct_answer": "A",
    "explanation": "Working through the problem step-by-step with the values -1, 2, 3, the correct answer is 2/13 - 3/13<i>i</i>.",
    "question_type": "Complex Numbers",
    "difficulty": null,
    "image_url": null,
    "chapter": "25",
    "lesson_id": "0090877d-e7d2-4ac4-80b4-87a42502a214",
    "section": "math"
  },
  {
    "id": 135,
    "test_number": 1,
    "question_number": 60,
    "question_text": "The rectangular container shown below has a small compartment for water created by a rectangular dividing wall of negligible width. One face of the dividing wall, shown shaded, has an area of 39 square inches. What is the volume, in cubic inches, of the larger compartment?",
    "choices": [
      "F. 180",
      "B. 195",
      "C. 390",
      "D. 450",
      "E. 540"
    ],
    "correct_answer": "J",
    "explanation": "Working through the problem step-by-step with the values 39, the correct answer is .",
    "question_type": "Geometry Part 2 - Volume",
    "difficulty": null,
    "image_url": "https://rabavobdklnwvwsldbix.supabase.co/storage/v1/object/public/test-images/m60.jpg",
    "chapter": "4",
    "lesson_id": "d2ae4a84-cb54-4006-8dee-8c325e443c2d",
    "section": "math"
  },
  {
    "id": 136,
    "test_number": 1,
    "question_number": 1,
    "passage_id": 50,
    "question_text": "The third paragraph (lines 33-46) marks a shift from the second paragraph\u2019s focus on Murali\u2019s impressions of Vani to the rest of the passage\u2019s focus on:",
    "choices": [
      "A. Murali's life as a married man.",
      "B. Murali's concerns about marriage.",
      "C. Murali and Vani's courtship and its effects on others.",
      "D. Murali's characteristics and his family conflicts."
    ],
    "correct_answer": "C",
    "explanation": "Murali and Vani's courtship and its effects on others. best answers the question based on the evidence and context provided in the passage.",
    "difficulty": null,
    "chapter": null,
    "question_type": "Main Idea",
    "lesson_id": "25fb92b6-429e-4940-802a-e339ae3a47e1",
    "section": "reading"
  },
  {
    "id": 137,
    "test_number": 1,
    "question_number": 2,
    "passage_id": 50,
    "question_text": "Details in the second paragraph (lines 9-32) primarily characterize Vani as:",
    "choices": [
      "F. reserved but self-assured.",
      "G. severe and impolite.",
      "H. intelligent and apologetic.",
      "J. beautiful but unkempt."
    ],
    "correct_answer": "F",
    "explanation": "reserved but self-assured. best answers the question based on the evidence and context provided in the passage.",
    "difficulty": null,
    "chapter": null,
    "question_type": "Clear Evidence",
    "lesson_id": "ac4440f6-f391-4a04-9a5c-751a2e0ca5b7",
    "section": "reading"
  },
  {
    "id": 138,
    "test_number": 1,
    "question_number": 3,
    "passage_id": 50,
    "question_text": "Which of the following events mentioned in the passage occurred first chronologically?",
    "choices": [
      "A. The elders organized occasions in which Vani and Murali would be together.",
      "B. A friend suggested that Murali drive Vani home.",
      "C. Vani smiled at Murali without thinking about her teeth.",
      "D. Vani's brother burst into Murali's brother's home."
    ],
    "correct_answer": "B",
    "explanation": "A friend suggested that Murali drive Vani home. best answers the question based on the evidence and context provided in the passage.",
    "difficulty": null,
    "chapter": null,
    "question_type": "Chronological Order",
    "lesson_id": "25fb92b6-429e-4940-802a-e339ae3a47e1",
    "section": "reading"
  },
  {
    "id": 139,
    "test_number": 1,
    "question_number": 4,
    "passage_id": 50,
    "question_text": "As it is presented in the passage, the italicized portion <i>\"How are you? That's a beautiful sari. How are the children? I like this rice\"</i> (lines 20-21) most likely indicates:",
    "choices": [
      "F. the types of pleasantries that Murali would prepare in his head before meeting someone new.",
      "G. parts of a conversation between Murali and Vani when they were first introduced.",
      "H. comments typical of the kind that Vani would make when in public.",
      "J. secret thoughts that Murali imagined Vani to be thinking."
    ],
    "correct_answer": "H",
    "explanation": "comments typical of the kind that Vani would make when in public. best answers the question based on the evidence and context provided in the passage.",
    "difficulty": null,
    "chapter": null,
    "question_type": "Clear Evidence",
    "lesson_id": "ac4440f6-f391-4a04-9a5c-751a2e0ca5b7",
    "section": "reading"
  },
  {
    "id": 140,
    "test_number": 1,
    "question_number": 5,
    "passage_id": 50,
    "question_text": "According to the passage, one similarity between Murali and Vani is that both:",
    "choices": [
      "A. enjoyed eating spicy food.",
      "B. were born in New York City.",
      "C. had a passion for cooking.",
      "D. worked at a medical clinic."
    ],
    "correct_answer": "A",
    "explanation": "According to the passage, enjoyed eating spicy food.. This information is directly stated in the text.",
    "difficulty": null,
    "chapter": null,
    "question_type": "Clear Evidence",
    "lesson_id": "ac4440f6-f391-4a04-9a5c-751a2e0ca5b7",
    "section": "reading"
  }
]